{
  "meta": {
    "source": "Ozon Global official calculator",
    "url": "https://globalcalculator.ozon.ru/",
    "originCountry": "China",
    "originCity": "Shenzhen",
    "destinationCountry": "Russia",
    "currency": "CNY",
    "notes": "This file stores official calculator calibration for visible services, delivery time, badges, and sample-level exclusions. XLSX is still used for candidate rates, but services excluded by a matched calculator sample must not affect default sorting."
  },
  "samples": [
    {
      "sampleId": "cn_sz_ru_1x1x1_50g_cny1",
      "input": {
        "lengthCm": 1,
        "widthCm": 1,
        "heightCm": 1,
        "weightG": 50,
        "price": 1
      },
      "excludedDeliveryMethodCodes": [
        "GUOO_GUOO_EXPRESS_EXTRA_SMALL"
      ],
      "services": [
        {
          "deliveryMethodCode": "CHINA_POST_CHINA_POST_TO_PUDO_ECONOMY_GROUND_DELIVERY",
          "officialDisplayName": "China Post to PUDO Economy",
          "calculatorPrice": 3.2,
          "badges": ["cheapest"],
          "variants": [
            {
              "variantCode": "PUDO",
              "officialName": "China Post to PUDO Economy",
              "deliveryTarget": "pickup_point",
              "deliveryDays": { "min": 13, "max": 20 },
              "deliveryTimeText": "from 13-20 days",
              "pickupText": "pickup point in your city",
              "chargeWeightText": "physical weight",
              "batteryPolicy": "allowed"
            }
          ]
        },
        {
          "deliveryMethodCode": "ATC_ATC_ECONOMY_EXTRA_SMALL",
          "officialDisplayName": "ATC Economy Extra Small",
          "calculatorPrice": 3.8,
          "variants": [
            {
              "variantCode": "COURIER",
              "officialName": "ATC Economy Extra Small to Ozon courier delivery",
              "deliveryTarget": "courier",
              "deliveryDays": { "min": 15, "max": 20 },
              "deliveryTimeText": "from 15-20 days",
              "pickupText": "pickup point in your city",
              "chargeWeightText": "physical weight",
              "batteryPolicy": "forbidden"
            },
            {
              "variantCode": "PUDO",
              "officialName": "ATC Economy Extra Small to Ozon pick-up point",
              "deliveryTarget": "pickup_point",
              "deliveryDays": { "min": 15, "max": 20 },
              "deliveryTimeText": "from 15-20 days",
              "pickupText": "pickup point in your city",
              "chargeWeightText": "physical weight",
              "batteryPolicy": "allowed"
            }
          ]
        },
        {
          "deliveryMethodCode": "GUOO_GUOO_ECONOMY_EXTRA_SMALL",
          "officialDisplayName": "GUOO Economy Extra Small",
          "calculatorPrice": 4.3,
          "variants": [
            {
              "variantCode": "COURIER",
              "officialName": "GUOO Economy Extra Small Courier",
              "deliveryTarget": "courier",
              "deliveryDays": { "min": 5, "max": 10 },
              "deliveryTimeText": "from 5-10 days",
              "pickupText": "pickup point in your city",
              "chargeWeightText": "physical weight",
              "batteryPolicy": "forbidden",
              "badges": ["fastest"]
            },
            {
              "variantCode": "PUDO",
              "officialName": "GUOO Economy Extra Small PUDO",
              "deliveryTarget": "pickup_point",
              "deliveryDays": { "min": 15, "max": 20 },
              "deliveryTimeText": "from 15-20 days",
              "pickupText": "pickup point in your city",
              "chargeWeightText": "physical weight",
              "batteryPolicy": "allowed"
            }
          ]
        },
        {
          "deliveryMethodCode": "CEL_CEL_ECONOMY_EXTRA_SMALL",
          "officialDisplayName": "CEL Economy Extra Small",
          "calculatorPrice": 4.42,
          "variants": [
            {
              "variantCode": "COURIER",
              "officialName": "CEL Extra Small Economy Courier",
              "deliveryTarget": "courier",
              "deliveryDays": { "min": 20, "max": 25 },
              "deliveryTimeText": "from 20-25 days",
              "pickupText": "pickup point in your city",
              "chargeWeightText": "physical weight",
              "batteryPolicy": "allowed"
            },
            {
              "variantCode": "PUDO",
              "officialName": "CEL Extra Small Economy PUDO",
              "deliveryTarget": "pickup_point",
              "deliveryDays": { "min": 20, "max": 25 },
              "deliveryTimeText": "from 20-25 days",
              "pickupText": "pickup point in your city",
              "chargeWeightText": "physical weight",
              "batteryPolicy": "allowed"
            }
          ]
        }
      ]
    },
    {
      "sampleId": "cn_sz_ru_1x1x1_500g_cny1",
      "input": {
        "lengthCm": 1,
        "widthCm": 1,
        "heightCm": 1,
        "weightG": 500,
        "price": 1
      },
      "excludedDeliveryMethodCodes": [
        "GUOO_GUOO_EXPRESS_EXTRA_SMALL"
      ],
      "services": [
        {
          "deliveryMethodCode": "ATC_ATC_ECONOMY_EXTRA_SMALL",
          "officialDisplayName": "ATC Economy Extra Small",
          "calculatorPrice": 14.6,
          "badges": ["cheapest"],
          "variants": [
            {
              "variantCode": "COURIER",
              "officialName": "ATC Economy Extra Small to Ozon courier delivery",
              "deliveryTarget": "courier",
              "deliveryDays": { "min": 15, "max": 20 },
              "deliveryTimeText": "from 15-20 days",
              "pickupText": "pickup point in your city",
              "chargeWeightText": "physical weight",
              "batteryPolicy": "forbidden"
            },
            {
              "variantCode": "PUDO",
              "officialName": "ATC Economy Extra Small to Ozon pick-up point",
              "deliveryTarget": "pickup_point",
              "deliveryDays": { "min": 15, "max": 20 },
              "deliveryTimeText": "from 15-20 days",
              "pickupText": "pickup point in your city",
              "chargeWeightText": "physical weight",
              "batteryPolicy": "allowed"
            }
          ]
        },
        {
          "deliveryMethodCode": "CHINA_POST_CHINA_POST_TO_PUDO_ECONOMY_GROUND_DELIVERY",
          "officialDisplayName": "China Post to PUDO Economy",
          "calculatorPrice": 14.9,
          "variants": [
            {
              "variantCode": "PUDO",
              "officialName": "China Post to PUDO Economy",
              "deliveryTarget": "pickup_point",
              "deliveryDays": { "min": 13, "max": 20 },
              "deliveryTimeText": "from 13-20 days",
              "pickupText": "pickup point in your city",
              "chargeWeightText": "physical weight",
              "batteryPolicy": "allowed"
            }
          ]
        },
        {
          "deliveryMethodCode": "GUOO_GUOO_ECONOMY_EXTRA_SMALL",
          "officialDisplayName": "GUOO Economy Extra Small",
          "calculatorPrice": 16,
          "variants": [
            {
              "variantCode": "COURIER",
              "officialName": "GUOO Economy Extra Small Courier",
              "deliveryTarget": "courier",
              "deliveryDays": { "min": 5, "max": 10 },
              "deliveryTimeText": "from 5-10 days",
              "pickupText": "pickup point in your city",
              "chargeWeightText": "physical weight",
              "batteryPolicy": "forbidden",
              "badges": ["fastest"]
            },
            {
              "variantCode": "PUDO",
              "officialName": "GUOO Economy Extra Small PUDO",
              "deliveryTarget": "pickup_point",
              "deliveryDays": { "min": 15, "max": 20 },
              "deliveryTimeText": "from 15-20 days",
              "pickupText": "pickup point in your city",
              "chargeWeightText": "physical weight",
              "batteryPolicy": "allowed"
            }
          ]
        },
        {
          "deliveryMethodCode": "CEL_CEL_ECONOMY_EXTRA_SMALL",
          "officialDisplayName": "CEL Economy Extra Small",
          "calculatorPrice": 16.12,
          "variants": [
            {
              "variantCode": "COURIER",
              "officialName": "CEL Extra Small Economy Courier",
              "deliveryTarget": "courier",
              "deliveryDays": { "min": 20, "max": 25 },
              "deliveryTimeText": "from 20-25 days",
              "pickupText": "pickup point in your city",
              "chargeWeightText": "physical weight",
              "batteryPolicy": "allowed"
            },
            {
              "variantCode": "PUDO",
              "officialName": "CEL Extra Small Economy PUDO",
              "deliveryTarget": "pickup_point",
              "deliveryDays": { "min": 20, "max": 25 },
              "deliveryTimeText": "from 20-25 days",
              "pickupText": "pickup point in your city",
              "chargeWeightText": "physical weight",
              "batteryPolicy": "allowed"
            }
          ]
        }
      ]
    },
    {
      "sampleId": "cn_sz_ru_1x1x1_5000g_cny1",
      "input": {
        "lengthCm": 1,
        "widthCm": 1,
        "heightCm": 1,
        "weightG": 5000,
        "price": 1
      },
      "excludedDeliveryMethodCodes": [
        "CHINA_POST_CHINA_POST_EPARCEL_ECONOMY"
      ],
      "services": [
        {
          "deliveryMethodCode": "GBS_GBS_ECONOMY_BUDGET",
          "officialDisplayName": "GBS Economy Budget",
          "calculatorPrice": 107.4,
          "badges": ["cheapest"],
          "variants": [
            {
              "variantCode": "PUDO",
              "officialName": "B2C express full to pick-up points / PUDO",
              "deliveryTarget": "pickup_point",
              "deliveryDays": { "min": 20, "max": 25 },
              "deliveryTimeText": "from 20-25 days",
              "pickupText": "pickup point in your city",
              "chargeWeightText": "physical weight",
              "batteryPolicy": "allowed"
            }
          ]
        },
        {
          "deliveryMethodCode": "ATC_ATC_ECONOMY_BUDGET",
          "officialDisplayName": "ATC Economy Budget",
          "calculatorPrice": 108,
          "variants": [
            {
              "variantCode": "PUDO",
              "officialName": "ATC Economy Budget to Ozon pick-up point",
              "deliveryTarget": "pickup_point",
              "deliveryDays": { "min": 20, "max": 25 },
              "deliveryTimeText": "from 20-25 days",
              "pickupText": "pickup point in your city",
              "chargeWeightText": "physical weight",
              "batteryPolicy": "allowed"
            },
            {
              "variantCode": "COURIER",
              "officialName": "ATC Economy Budget to Ozon courier delivery",
              "deliveryTarget": "courier",
              "deliveryDays": { "min": 20, "max": 25 },
              "deliveryTimeText": "from 20-25 days",
              "pickupText": "pickup point in your city",
              "chargeWeightText": "physical weight",
              "batteryPolicy": "forbidden"
            }
          ]
        },
        {
          "deliveryMethodCode": "RETS_RETS_ECONOMY_BUDGET",
          "officialDisplayName": "RETS Economy Budget",
          "calculatorPrice": 112.32,
          "variants": [
            {
              "variantCode": "COURIER",
              "officialName": "RETS Economy Budget Courier",
              "deliveryTarget": "courier",
              "deliveryDays": { "min": 9, "max": 14 },
              "deliveryTimeText": "from 9-14 days",
              "pickupText": "pickup point in your city",
              "chargeWeightText": "physical weight",
              "batteryPolicy": "forbidden"
            }
          ]
        }
      ]
    }
  ],
  "boundarySamples": [
    {
      "sampleId": "weight_500g_cny1",
      "input": { "lengthCm": 1, "widthCm": 1, "heightCm": 1, "weightG": 500, "price": 1 },
      "observed": {
        "extraSmallAvailable": true,
        "atcEconomyExtraSmallPrice": 14.6,
        "chinaPostPudoEconomyPrice": 14.9,
        "guooEconomyExtraSmallPrice": 16,
        "celEconomyExtraSmallPrice": 16.12
      }
    },
    {
      "sampleId": "weight_501g_cny1",
      "input": { "lengthCm": 1, "widthCm": 1, "heightCm": 1, "weightG": 501, "price": 1 },
      "observed": {
        "extraSmallAvailable": false,
        "nextPrimaryBand": "Small",
        "examples": ["ATC Express Small", "CEL Standard Small", "GUOO Economy Small", "GBS Economy Small"]
      }
    },
    {
      "sampleId": "weight_2000g_cny1",
      "input": { "lengthCm": 1, "widthCm": 1, "heightCm": 1, "weightG": 2000, "price": 1 },
      "observed": {
        "smallAvailable": true,
        "examples": ["ATC Express Small", "CEL Standard Small", "GUOO Economy Small"]
      }
    },
    {
      "sampleId": "weight_2001g_cny1",
      "input": { "lengthCm": 1, "widthCm": 1, "heightCm": 1, "weightG": 2001, "price": 1 },
      "observed": {
        "bigAvailable": true,
        "examples": ["CEL Standard Big", "OYX Economy Big"]
      }
    },
    {
      "sampleId": "weight_5000g_cny1",
      "input": { "lengthCm": 1, "widthCm": 1, "heightCm": 1, "weightG": 5000, "price": 1 },
      "observed": {
        "budgetAvailable": true,
        "chinaPostEparcelExcluded": true,
        "gbsEconomyBudgetPrice": 107.4,
        "atcEconomyBudgetPrice": 108
      }
    }
  ],
  "weightBands": [
    { "name": "Extra Small", "minWeightG": 1, "maxWeightG": 500 },
    { "name": "Small", "minWeightG": 501, "maxWeightG": 2000 },
    { "name": "Big", "minWeightG": 2001, "maxWeightG": 30000 },
    { "name": "Premium Small", "minWeightG": 1, "maxWeightG": 5000 },
    { "name": "Premium Big", "minWeightG": 5001, "maxWeightG": 30000 },
    { "name": "Budget", "minWeightG": 501, "maxWeightG": 30000 }
  ]
}
